MANIFEST.in
README.md
setup.cfg
setup.py
argoap/ARGs_OAP.py
argoap/README.md
argoap/__init__.py
argoap/argoap_pipeline_stageone_version2
argoap/argoap_pipeline_stageone_version2.3
argoap/argoap_pipeline_stagetwo_version2
argoap/index.rst
argoap/stage_one.py
argoap/stage_two.py
argoap.egg-info/PKG-INFO
argoap.egg-info/SOURCES.txt
argoap.egg-info/dependency_links.txt
argoap.egg-info/entry_points.txt
argoap.egg-info/top_level.txt
argoap/DB/KO30_DIAMOND.dmnd
argoap/DB/SARG.2.2.diamondv0.9.24.dmnd
argoap/DB/SARG.2.2.fasta
argoap/DB/SARG.2.2.fasta.phr
argoap/DB/SARG.2.2.fasta.pin
argoap/DB/SARG.2.2.fasta.psq
argoap/DB/all_KO30_name.list
argoap/DB/gg85.fasta
argoap/DB/gg85_yinxiaole.fasta.mmi
argoap/DB/structure_20181107.LIST
argoap/DB/update_45_sarg2.0_16s.table_201704.txt
argoap/DB/update_45_sarg2.0_cell.table_201704.txt
argoap/bin/Fq2fa.pl
argoap/bin/blastx
argoap/bin/copy_correction.pl
argoap/bin/de-replicate.pl
argoap/bin/diamond
argoap/bin/diamondv0.9.24
argoap/bin/divide_extract.fa_meta_data_online.pl
argoap/bin/extract_usearch_reads.pl
argoap/bin/fastp
argoap/bin/merge_extracted_fa_update_metadate.v2.3.pl
argoap/bin/minimap2
argoap/bin/obtain_community.pl
argoap/bin/samtools
argoap/bin/bbmap/README.md
argoap/bin/bbmap/a_sample_mt.sh
argoap/bin/bbmap/addadapters.sh
argoap/bin/bbmap/addssu.sh
argoap/bin/bbmap/adjusthomopolymers.sh
argoap/bin/bbmap/alltoall.sh
argoap/bin/bbmap/analyzeaccession.sh
argoap/bin/bbmap/analyzegenes.sh
argoap/bin/bbmap/analyzesketchresults.sh
argoap/bin/bbmap/applyvariants.sh
argoap/bin/bbmap/bbcms.sh
argoap/bin/bbmap/bbcountunique.sh
argoap/bin/bbmap/bbduk.sh
argoap/bin/bbmap/bbest.sh
argoap/bin/bbmap/bbfakereads.sh
argoap/bin/bbmap/bbmap.sh
argoap/bin/bbmap/bbmapskimmer.sh
argoap/bin/bbmap/bbmask.sh
argoap/bin/bbmap/bbmerge-auto.sh
argoap/bin/bbmap/bbmerge.sh
argoap/bin/bbmap/bbnorm.sh
argoap/bin/bbmap/bbrealign.sh
argoap/bin/bbmap/bbrename.sh
argoap/bin/bbmap/bbsketch.sh
argoap/bin/bbmap/bbsplit.sh
argoap/bin/bbmap/bbsplitpairs.sh
argoap/bin/bbmap/bbstats.sh
argoap/bin/bbmap/bbversion.sh
argoap/bin/bbmap/bbwrap.sh
argoap/bin/bbmap/bloomfilter.sh
argoap/bin/bbmap/calcmem.sh
